tkfontawesome_mizraith/__init__.py
tkfontawesome_mizraith/svgs.py
tkfontawesome_mizraith/svgs/consolidate.py
tkfontawesome_mizraith-0.3.dist-info/METADATA
tkfontawesome_mizraith-0.3.dist-info/WHEEL
tkfontawesome_mizraith-0.3.dist-info/licenses/LICENSE
tkfontawesome_mizraith-0.3.dist-info/RECORD
