Metadata-Version: 2.3
Name: tkfontawesome_mizraith
Version: 0.3
Summary: Use any of the 2k+ free FontAwesome icons in your tkinter application without the scikit bloatware.
Project-URL: Homepage, https://github.com/mizraith/TkFontAwesome
Project-URL: Repository, https://github.com/mizraith/TkFontAwesome
Project-URL: Issues, https://github.com/mizraith/TkFontAwesome/issues
Author-email: Israel Dryer <israel.dryer@gmail.com>
License: MIT License
License-File: LICENSE
Keywords: fontawesome,icons,svg,tkinter,ttk
Classifier: License :: OSI Approved :: MIT License
Classifier: Operating System :: OS Independent
Classifier: Programming Language :: Python :: 3
Requires-Python: >=3.10
Requires-Dist: lxml==5.2.1
Requires-Dist: tksvg==0.7.4
